qstd_config/__init__.py
qstd_config/exceptions.py
qstd_config/logger.py
qstd_config/manager.py
qstd_config/proxy.py
qstd_config/py.typed
qstd_config/utils.py
qstd_config/loader/__init__.py
qstd_config/loader/base.py
qstd_config/loader/chain_loader.py
qstd_config/loader/env_field.py
qstd_config/loader/env_loader.py
qstd_config/loader/factory.py
qstd_config/loader/file_loader.py
qstd_config/loader/file_loader_registry.py
qstd_config/loader/utils.py
qstd_config/merge_strategy/__init__.py
qstd_config/merge_strategy/base.py
qstd_config/merge_strategy/deep_merge.py
qstd_config/storage/__init__.py
qstd_config/storage/base.py
qstd_config/storage/in_memory.py
qstd_config/storage/multiprocessing_dict.py
qstd_config/storage/types.py
qstd_config-1.0.1.dist-info/licenses/LICENSE
qstd_config-1.0.1.dist-info/METADATA
qstd_config-1.0.1.dist-info/WHEEL
qstd_config-1.0.1.dist-info/top_level.txt
qstd_config-1.0.1.dist-info/RECORD
