Metadata-Version: 2.4
Name: qstd-config
Version: 1.0.1
Summary: Application configuration manager
Author-email: QuisEgoSum <subbotin.evdokim@gmail.com>
License-Expression: MIT
Project-URL: Homepage, https://github.com/QuisEgoSum/qstd-config
Project-URL: Repository, https://github.com/QuisEgoSum/qstd-config
Keywords: config,yaml,env
Classifier: Programming Language :: Python :: 3
Classifier: Programming Language :: Python :: 3.9
Classifier: Programming Language :: Python :: 3.10
Classifier: Programming Language :: Python :: 3.11
Classifier: Programming Language :: Python :: 3.12
Classifier: Operating System :: OS Independent
Classifier: Development Status :: 5 - Production/Stable
Requires-Python: >=3.9
License-File: LICENSE
Requires-Dist: pydantic>=2.0.0
Requires-Dist: pydantic_core>=2.0.0
Requires-Dist: PyYAML>=6.0
Provides-Extra: dev
Requires-Dist: pytest<9.0,>=8.0; extra == "dev"
Requires-Dist: tox>=4.26.0; extra == "dev"
Requires-Dist: pytest-cov<7.0,>=6.0; extra == "dev"
Requires-Dist: ruff>=0.11.2; extra == "dev"
Requires-Dist: black>=25.1.0; extra == "dev"
Requires-Dist: build>=1.2.2; extra == "dev"
Requires-Dist: twine>=6.1.0; extra == "dev"
Dynamic: license-file
